<?xml version='1.0' encoding='utf-8'?>
<Map>
	<Zone>
		<zonedef id="100" width="2" height="2" x="58" y="38" type="3" />
	</Zone>
	<RelivePosition />
	<ArmyEquipArea />
	<NpcRect>
		<rect id="1" width="6" height="6" x="19" y="17" />
		<rect id="2" width="5" height="5" x="47" y="24" />
		<rect id="3" width="4" height="5" x="28" y="33" />
	</NpcRect>
	<Npc>
		<npc id="19108" name="怪物名字" x="19" y="17" num="10" interval="86400">
			<rect id="1" />
		</npc>
		<npc id="19109" name="怪物名字" x="47" y="24" num="10" interval="86400">
			<rect id="2" />
		</npc>
		<npc id="19110" name="怪物名字" x="28" y="33" num="10" interval="86400">
			<rect id="3" />
		</npc>
	</Npc>
	<Way>
	</Way>
</Map>